katsdptelstate/__init__.py
katsdptelstate/backend.py
katsdptelstate/encoding.py
katsdptelstate/endpoint.py
katsdptelstate/errors.py
katsdptelstate/memory.py
katsdptelstate/py.typed
katsdptelstate/rdb_reader.py
katsdptelstate/rdb_utility.py
katsdptelstate/rdb_writer.py
katsdptelstate/rdb_writer_base.py
katsdptelstate/redis.py
katsdptelstate/telescope_state.py
katsdptelstate/telescope_state_base.py
katsdptelstate/utils.py
katsdptelstate/aio/__init__.py
katsdptelstate/aio/backend.py
katsdptelstate/aio/memory.py
katsdptelstate/aio/rdb_writer.py
katsdptelstate/aio/redis.py
katsdptelstate/aio/telescope_state.py
katsdptelstate/aio/test/__init__.py
katsdptelstate/aio/test/test_rdb_writer.py
katsdptelstate/aio/test/test_telescope_state.py
katsdptelstate/lua_scripts/add_mutable.lua
katsdptelstate/lua_scripts/get.lua
katsdptelstate/lua_scripts/get_indexed.lua
katsdptelstate/lua_scripts/set_immutable.lua
katsdptelstate/lua_scripts/set_indexed.lua
katsdptelstate/test/__init__.py
katsdptelstate/test/test_encoding.py
katsdptelstate/test/test_endpoint.py
katsdptelstate/test/test_rdb_handling.py
katsdptelstate/test/test_telescope_state.py
katsdptelstate-1.0.0.dist-info/licenses/LICENSE
katsdptelstate-1.0.0.dist-info/METADATA
katsdptelstate-1.0.0.dist-info/WHEEL
katsdptelstate-1.0.0.dist-info/top_level.txt
katsdptelstate-1.0.0.dist-info/RECORD
