Metadata-Version: 2.4
Name: katsdptelstate
Version: 1.0.0
Summary: Karoo Array Telescope - Telescope State Client
Home-page: https://github.com/ska-sa/katsdptelstate
Author: MeerKAT SDP team
Author-email: sdpdev+katsdptelstate@sarao.ac.za
License: BSD-3-Clause
Keywords: meerkat sarao
Platform: OS Independent
Classifier: Development Status :: 5 - Production/Stable
Classifier: Intended Audience :: Developers
Classifier: Operating System :: OS Independent
Classifier: Programming Language :: Python
Classifier: Programming Language :: Python :: 3
Classifier: Topic :: Software Development :: Libraries :: Python Modules
Classifier: Topic :: Scientific/Engineering :: Astronomy
Requires-Python: >=3.7
License-File: LICENSE
Requires-Dist: hiredis
Requires-Dist: importlib-resources; python_version < "3.9"
Requires-Dist: msgpack
Requires-Dist: numpy
Requires-Dist: redis>=4.2
Requires-Dist: six>=1.12
Provides-Extra: rdb
Requires-Dist: rdbtools; extra == "rdb"
Requires-Dist: python-lzf; extra == "rdb"
Requires-Dist: setuptools; python_version >= "3.12" and extra == "rdb"
Provides-Extra: aio
Provides-Extra: test
Requires-Dist: async_timeout>=1.3.0; extra == "test"
Requires-Dist: fakeredis[lua]>=2.0.0; extra == "test"
Requires-Dist: pytest; extra == "test"
Requires-Dist: pytest-asyncio>=0.17.0; extra == "test"
Dynamic: author
Dynamic: author-email
Dynamic: classifier
Dynamic: description
Dynamic: description-content-type
Dynamic: home-page
Dynamic: keywords
Dynamic: license
Dynamic: license-file
Dynamic: platform
Dynamic: provides-extra
Dynamic: requires-dist
Dynamic: requires-python
Dynamic: summary
